{
  "id": 8,
  "title": "Surf, cultura y vida isleña: por qué Ngor es mucho más que un surf spot",
  "slug": "surf-culture-island-life-ngor",
  "category": "Island Life & Surf Camp",
  "focus_keyword": "senegal surf camp",
  "secondary_keywords": [
    "Ngor Island Senegal",
    "surf and culture Senegal"
  ],
  "type": "hero",
  "hero_image_prompt": "Colorful Ngor Island street by the sea, locals and surfers mingling, pirogue boats, fresh food, ocean breeze, no-car tranquility, warm sunset tones, culturally rich surf travel atmosphere, authentic Senegal lifestyle, documentary-meets-luxury editorial style.",
  "target_audience": "Experience-driven travelers who want culture, authenticity, and relaxation alongside surfing",
  "lang": "es",
  "meta_description": "Surf, cultura y vida isleña en Ngor: olas míticas, ambiente sin coches y surf camp premium frente a Dakar, Senegal.",
  "content_markdown": "# Surf, cultura y vida isleña: por qué Ngor es mucho más que un surf spot\n\nCon las primeras luces del día, Ngor no se despierta con tráfico. Se despierta con el golpeteo suave de los remos contra las piraguas de madera, con el grito de las gaviotas sobre la roca volcánica oscura y con el aroma del café Touba que llega desde alguna terraza cercana. Desde la Dakar continental, la travesía dura apenas unos minutos, pero el ambiente cambia por completo. Los coches desaparecen. El ruido baja. El tiempo afloja su presión.\n\nEso es lo que más sorprende a quienes llegan a la isla de Ngor, en Senegal. Vienen por las olas famosas ,las mismas aguas inmortalizadas en *The Endless Summer* en 1964, y descubren algo más profundo: un ritmo isleño que relaja el cuerpo y afina los sentidos. Entre sesiones en Ngor Right o Ngor Left, comes pescado a la brasa junto al mar, intercambias sonrisas con los vecinos en callejuelas de arena y ves cómo el sol cae sobre el Atlántico desde una tumbona junto a la piscina.\n\nUn buen surf trip te da olas. Uno realmente grande cambia la manera en que habitas un lugar. Ngor hace eso sin hacer ruido, marea a marea.\n\n## Por qué un surf camp en Senegal, en la isla de Ngor, se siente diferente\n\nHay destinos de surf donde el campamento no es más que un sitio donde dormir entre baños. Ngor no es uno de ellos. Elegir un **surf camp en Senegal** en la isla de Ngor significa entrar en un entorno donde el surf está tejido en la vida cotidiana, en la identidad local y en el propio paisaje.\n\nLa primera diferencia es geográfica. Ngor se encuentra justo frente a la punta de la península de Almadies, en Dakar: lo bastante cerca de la ciudad como para seguir conectado, pero separada por una corta travesía en barca que lo cambia todo. En cuanto llegas, se impone la calma sin coches de la isla. Aquí se va andando a todas partes. Las tablas descansan apoyadas en las paredes. Los niños juegan en los callejones. Los pescadores ordenan las redes junto a la orilla. El Atlántico nunca queda lejos de la vista, ni del oído.\n\nLuego están las olas. Ngor Right es uno de los picos más icónicos de África Occidental: rápido, limpio y muy fotogénico, con una historia que añade una chispa especial a cada sesión. Ngor Left tiene su propio carácter y su propio nivel de exigencia, aportando variedad en una zona compacta. Para principiantes y para intermedios que quieren progresar, alojarse cerca marca una diferencia enorme. No pasas el viaje atrapado en traslados ni tratando de descifrar una costa complicada. Estás cerca del line-up, cerca de tus coaches y cerca de las condiciones que importan.\n\nEn Ngor Surfcamp Teranga, esa cercanía forma parte de la experiencia. El camp combina confort premium con la calidez por la que Senegal es conocido. “Teranga” no es solo una palabra bonita para hablar de hospitalidad; aquí es un principio vivo. Después de surfear, vuelves a vistas al mar, piscina y un espacio que invita al sistema nervioso a bajar revoluciones. El video coaching añade otra capa importante. En lugar de consejos vagos, recibes feedback real y útil: dónde dudaste en el takeoff, cómo cambió tu postura, por qué una sección abrió y otra cerró. La progresión se vuelve visible.\n\nY como la propia isla tiene tanta atmósfera, el viaje nunca se siente plano ni unidimensional. No estás entrando en una burbuja de surf aislada del mundo. Estás entrando en un lugar con textura, memoria y un pulso propio. Por eso un **surf camp en Senegal** en Ngor suele quedarse en la memoria mucho después de la última ola.\n\n## Isla de Ngor, Senegal: una isla pequeña con un ritmo profundo\n\nPara entender por qué Ngor engancha, hay que bajarse de la tabla un momento y prestar atención a las horas entre sesiones. La isla es pequeña, pero transmite una sensación muy rara hoy en día: la de un lugar completo. La mañana, el mediodía y la tarde tienen personalidad propia. El día no se mide solo por mareas y partes; también por la luz, por los olores, por la conversación y por la forma en que el mar ordena la vida.\n\nPor la mañana temprano, el aire suele sentirse fresco y limpio. La actividad empieza sin estridencias. Hay movimiento, sí, pero no prisa. Se oye a la gente preparar el día, a las embarcaciones moverse, a las puertas abrirse. Si sales a caminar antes del desayuno, entiendes enseguida que Ngor no funciona como un simple decorado para surfistas. Es una comunidad viva. El surf está presente, pero no monopoliza el sentido del lugar.\n\nA mediodía, la isla se vuelve más luminosa, más abierta. El sol cae fuerte sobre las fachadas claras, la arena de los caminos refleja la luz y el mar cambia de color según la marea y el viento. Después de surfear, el cuerpo pide algo sencillo: sombra, agua, comida fresca. Y ahí Ngor brilla. Un pescado recién hecho, arroz, verduras, fruta, una pausa sin pantallas ni desplazamientos largos. Ese tipo de descanso tiene un valor enorme cuando viajas para surfear. No solo recuperas energía: vuelves a tu eje.\n\nPor la tarde, la isla entra en una versión todavía más serena de sí misma. La luz se vuelve dorada, las conversaciones se alargan, el horizonte gana profundidad. Incluso si no entras al agua a última hora, merece la pena quedarse cerca del mar y mirar. En muchos destinos de surf, el tiempo fuera del agua se llena con ruido, consumo o logística. En Ngor, en cambio, el entorno te invita a hacer menos y a sentir más. Para muchos surfers, esa es la parte inesperada del viaje: descubrir que el descanso también forma parte del surfing.\n\nLa dimensión cultural también pesa. Estás en Senegal, no en un resort genérico con olas delante. Eso significa que el viaje tiene contexto. Tiene sabores, lenguas, gestos, música, maneras de recibir y de compartir. Tiene una relación visible entre el mar y la vida cotidiana. Esa autenticidad no necesita ser exhibida; simplemente está ahí. Y cuando un destino no fuerza su encanto, suele resultar todavía más potente.\n\n## Olas con historia: de *The Endless Summer* a tus sesiones en Ngor Right y Ngor Left\n\nHay spots famosos que decepcionan cuando por fin los ves. Son nombres grandes sostenidos más por el mito que por la realidad. Ngor no entra en esa categoría. La historia está ahí, claro, pero las olas también responden.\n\n**HECHO:** Ngor entró en la historia del surf gracias a su aparición en *The Endless Summer*, la película de 1964 que presentó a muchas audiencias globales el viaje surfista internacional. Más de sesenta años después, la isla sigue siendo uno de los spots de surf más conocidos de África Occidental, no solo por nostalgia, sino porque Ngor Right y Ngor Left continúan ofreciendo experiencias de olas muy distintivas para diferentes niveles.\n\nPara muchos surfistas, el primer vínculo con Ngor llega a través de *The Endless Summer*. La película convirtió este rincón en parte del imaginario global del surf y lo dejó asociado para siempre a una idea de aventura, exploración y elegancia natural. Pero lo interesante es que Ngor no se ha quedado congelado en esa postal. Sigue siendo un lugar vivo, con sesiones reales, aprendizaje real y una conexión muy directa entre pasado y presente.\n\nNgor Right concentra buena parte de esa magia. Es una derecha de referencia, de las que despiertan respeto y ganas a la vez. Cuando está bien, ofrece velocidad, línea y secciones que piden decisión. Tiene esa cualidad que tantos surfers buscan: una ola que te obliga a estar presente. No basta con remar y levantarse. Hay que leer, colocarse, comprometerse. Y precisamente por eso deja huella.\n\nNgor Left equilibra el cuadro. Aporta otra lectura del pico, otro ángulo, otra forma de trabajar la ola. Para quienes están progresando, contar con dos opciones tan conocidas y relativamente cercanas es una ventaja enorme. Puedes comparar sensaciones, adaptar objetivos y entender mejor cómo cambian las condiciones. Para quienes ya tienen experiencia, esa variedad mantiene el interés y evita que el viaje se limite a repetir siempre la misma fórmula.\n\nAdemás, surfear en un sitio con pedigree no es solo una cuestión de ego surfero. También puede ser una motivación real para mejorar. Cuando sabes que estás entrando en un spot con historia, prestas más atención. Observas más. Escuchas más. Te vuelves más consciente de cada detalle: la entrada, la corriente, el timing, la forma de la pared. Y esa atención, bien guiada, se traduce en progresión.\n\nAhí es donde el coaching marca diferencia. Tener a alguien que no solo conoce la ola, sino que sabe explicártela, acelera muchísimo el proceso. La lectura del spot deja de ser abstracta. De repente entiendes por qué una marea favorece una sección concreta, por qué conviene variar la posición en el pico o por qué tu takeoff se complica en ciertos momentos del baño. El surf deja de ser una sucesión de intentos y se convierte en aprendizaje consciente.\n\n## El valor de estar cerca: menos logística, más surf\n\nMuchos viajes de surf prometen olas, pero en la práctica consumen una parte enorme del día en desplazamientos, esperas y cambios de plan. Sales temprano, cargas tablas, cruzas media costa, llegas cansado, vuelves tarde. A veces funciona, pero rara vez ayuda a surfear mejor. Ngor propone otra lógica.\n\nEstar alojado en la isla significa reducir la fricción. Y cuando la fricción baja, la calidad del viaje sube. Tienes más margen para observar el mar, más flexibilidad para elegir el momento de entrar y más energía disponible para lo importante. No estás en modo expedición constante. Estás instalado en el ritmo del spot.\n\nEso beneficia a todos los niveles. Si eres principiante, simplifica el aprendizaje. Menos variables, menos estrés, más capacidad para concentrarte en fundamentos como la remada, la colocación, el takeoff o la postura. Si estás en nivel intermedio, la proximidad te permite repetir, ajustar y volver a probar con intención. Y si ya tienes experiencia, agradeces algo básico pero poco frecuente: poder organizar sesiones de calidad sin convertir cada día en una operación logística.\n\nTambién cambia la relación con el descanso. Entre baños, no te refugias en un parking ni improvisas una comida rápida. Vuelves a un espacio cómodo, con vistas al mar, piscina y ambiente tranquilo. Eso no es un lujo superficial. Es parte del rendimiento. Un cuerpo descansado aprende mejor, reacciona mejor y disfruta más.\n\n**CONSEJO:** Lleva un par de sandalias buenas, un equipo de surf seguro para arrecifes y ropa en la que realmente quieras relajarte. Ngor no es un lugar para llevar demasiado equipaje. Algodón ligero, traje de baño, protección solar y algo cómodo para las cenas son suficientes. Cuanto más simple viajes, más fácil será deslizarte en el ritmo isleño, y ese ritmo es uno de los mayores regalos del lugar.\n\nEn Ngor Surfcamp Teranga, esa comodidad está pensada para surfers que valoran tanto la experiencia en el agua como lo que ocurre fuera de ella. La idea no es llenar el día de actividad por llenar, sino crear una base desde la que surfear mejor y vivir mejor el viaje. A veces, el auténtico premium no está en lo ostentoso, sino en lo bien resuelto.\n\n## Video coaching: ver tu surf para cambiarlo de verdad\n\nTodo surfer conoce esa sensación: sales del agua convencido de que una maniobra fue de una manera y luego descubres que no se parecía en nada a lo que imaginabas. El surf tiene ese punto engañoso. Desde dentro, muchas cosas se sienten mejor de lo que se ven. Por eso el video coaching es tan potente.\n\nEn un destino como Ngor, donde las olas tienen personalidad y el entorno invita a bajar el ritmo, analizar tus sesiones con calma multiplica el valor del viaje. No se trata solo de grabarte por curiosidad. Se trata de convertir cada baño en material útil. Ver dónde empiezas tarde, cómo colocas los pies, si tu mirada acompaña la línea o si tu postura frena la velocidad. Lo que en el agua parecía confuso, en pantalla se vuelve claro.\n\nPara surfers principiantes, esto acelera la comprensión. Conceptos que a veces cuestan semanas de interiorizar ,como el timing del takeoff o la importancia de la base, se vuelven evidentes en pocos minutos. Para intermedios, el análisis ayuda a romper techos habituales: giros sin terminar, falta de compresión, brazos desordenados, lectura pobre de la sección. Y para niveles más avanzados, el video permite afinar detalles que marcan una diferencia enorme.\n\nLo importante es que el feedback sea concreto y aplicable. No basta con decir “tienes que ir más fluido” o “te falta compromiso”. Hace falta traducir sensaciones a acciones: remar dos veces más, mirar antes hacia la salida, bajar el centro de gravedad, esperar medio segundo, entrar con más ángulo. Cuando el coaching baja a ese nivel de precisión, la mejora deja de depender solo de acumular horas.\n\nAdemás, hay algo motivador en ver tu progreso durante el propio viaje. No vuelves a casa con una idea vaga de haber mejorado; vuelves con imágenes, referencias y una comprensión más nítida de tu surf. Eso hace que la experiencia continúe incluso después de salir de Ngor.\n\n**EXPERT:** “Lo que hace memorable a Ngor no es solo la calidad del surf,” dice Sophie Renard, escritora especializada en viajes de surf. “Es la completitud del día. Surfeas una ola histórica, comes comida arraigada en el lugar, ves a los pescadores regresar al atardecer y te duermes con el sonido del Atlántico. Muy pocos destinos ofrecen esa continuidad entre el surf y la vida local.”\n\n## Teranga, mar y calma: el lujo de un surf trip bien vivido\n\nEn el mundo del surf, la palabra “premium” se usa con demasiada facilidad. A veces describe poco más que una decoración cuidada o una ubicación bonita. En Ngor Surfcamp Teranga, el valor premium tiene más que ver con cómo te hace sentir el lugar.\n\nLa hospitalidad senegalesa ,la famosa teranga, no se vive como un servicio frío y pulido, sino como una forma genuina de acogida. Eso cambia por completo el tono del viaje. No eres un cliente que entra y sale de una estructura impersonal. Eres un huésped en un entorno donde la atención importa, donde el detalle suma y donde la experiencia se construye con cercanía.\n\nLas vistas al mar ayudan, por supuesto. También la piscina, que añade una dimensión de descanso muy agradecida después de surfear. Pero lo que termina marcando la diferencia es la sensación de equilibrio. El camp te permite estar activo sin agotarte, socializar sin saturarte y descansar sin desconectarte del paisaje. Todo eso, en un lugar sin coches, con el océano siempre presente, tiene un efecto muy particular.\n\nPara muchos surfers hispanohablantes, acostumbrados a viajes donde prima la cantidad de baños o la búsqueda obsesiva del spot perfecto, Ngor ofrece una lección distinta. Aquí la calidad de la experiencia no depende solo del número de olas surfeadas. Depende también de cómo comes, cómo descansas, cómo observas y cómo te relacionas con el sitio. El viaje se vuelve más redondo.\n\nY eso no le quita intensidad al surf; al contrario. La suma de calma, comodidad y coaching hace que entres al agua con más foco. Menos ruido fuera suele significar más claridad dentro.\n\n## Mucho más que un destino: una forma de estar\n\nAl final, eso es lo que distingue a Ngor. No solo ofrece olas de nivel, historia surf y una ubicación singular frente a Dakar. Ofrece una forma distinta de vivir un surf trip. Más cercana. Más sensorial. Más humana.\n\nVienes por Ngor Right, por Ngor Left, por el eco de *The Endless Summer*, por la promesa de un **surf camp en Senegal** con comodidad y coaching. Y todo eso está. Pero además encuentras una isla donde el tiempo se ensancha, donde el mar organiza el día y donde la cultura local no es un accesorio, sino parte esencial de la experiencia.\n\nPor eso Ngor se queda contigo. No solo por una ola especialmente buena, ni por una foto bonita al atardecer. Se queda por la suma de pequeñas cosas: el sonido de las piraguas al amanecer, el café Touba en el aire, la caminata descalzo hacia el agua, el pescado junto al mar, el análisis de una sesión que te abre los ojos, la calma de una tarde sin coches ni prisas.\n\nUn buen surf trip te da recuerdos. Ngor te cambia un poco el ritmo por dentro.\n\n**RESUMEN:**\n- Ngor ofrece más que olas porque la vida isleña, la hospitalidad y la cultura moldean toda la experiencia surfista.\n- La ausencia de coches crea calma, ideal para principiantes y surfistas ocasionales que buscan verdadera recuperación.\n- Surfear aquí se inserta en una cultura costera viva, donde el conocimiento local de mareas, viento y ritmo oceánico aporta profundidad.\n- Los mejores viajes a Ngor combinan progresión en el agua con comidas, conversaciones y momentos lentos en tierra.\n\n**CHECKLIST:**\n- Elige el objetivo de surf adecuado para tu nivel antes de llegar\n- Empaca ligero, lleva protección solar fuerte y calzado sencillo\n- Aprende algunos saludos en francés o wolof\n- Usa video coaching para enfocarte en una o dos correcciones técnicas\n- Reserva energía para las mejores condiciones en lugar de surfear cada hora\n- Dedica tiempo a caminatas por la isla, comidas compartidas y momentos tranquilos al atardecer\n- Respeta el ritmo local, los espacios comunitarios y la vida laboral del mar\n\n## Preguntas frecuentes\n\n**¿Es Ngor Island un buen lugar para un primer viaje de surf en Senegal?**  \nSí, especialmente si eliges un campamento con guía y coaching. Ngor ofrece un entorno más tranquilo y más inmersivo que muchos destinos de surf más concurridos, y la presencia de Ngor Left hace que la isla sea accesible para muchos principiantes. Igual de importante, el entorno sin coches, el ritmo isleño y la atmósfera de apoyo reducen el estrés que a menudo acompaña a unas primeras vacaciones de surf. Para los principiantes, esa combinación de olas manejables, guía local y tiempo de descanso reparador puede hacer que aprender se sienta disfrutable en lugar de abrumador.\n\n**¿Qué hace diferente a Ngor de otros destinos de surf en África Occidental?**  \nNgor destaca porque combina importancia histórica en el surf, variedad de olas de calidad y un entorno cultural inusualmente rico. Tienes la famosa Ngor Right para surfistas experimentados, Ngor Left para una accesibilidad más amplia, y la atmósfera única de una isla habitada justo frente a Dakar. Si además sumas la hospitalidad senegalesa, una sólida cultura gastronómica y la ausencia de coches, el resultado se siente mucho más completo que una simple parada centrada solo en el surf. Es un destino donde la vida alrededor de las sesiones es tan memorable como el surf en sí.\n\n**¿Cuál es la mejor época para alojarse en un campamento de surf en Senegal, en Ngor Island?**  \nEl mejor momento depende de tu nivel, tus objetivos y el tipo de condiciones que buscas. Más importante que perseguir un único mes “perfecto” es alojarte con gente que sepa leer los patrones locales de swell, marea y viento día a día. Ngor recompensa el conocimiento local. Si quieres ayuda para elegir el mejor periodo para tu viaje, \n o ponte en contacto directamente con el campamento para recibir orientación según tu nivel de experiencia y tus expectativas.\n",
  "word_count_estimate": 2945,
  "original_en_slug": "surf-culture-island-life-ngor"
}