{
  "id": 16,
  "title": "Surf camp in Senegal per principianti: Ngor Island è una buona scelta?",
  "slug": "senegal-surf-camp-for-beginners",
  "category": "Coaching & Progression",
  "focus_keyword": "senegal surf camp for beginners",
  "secondary_keywords": [
    "beginner surf camp senegal",
    "learn surfing in senegal"
  ],
  "type": "seo",
  "hero_image_prompt": "Friendly surf camp scene with novice guests carrying softboards along Ngor Island shore, coach smiling, calm blue water, palm-fringed village details, premium yet relaxed atmosphere, confidence-building travel energy, natural light, authentic documentary realism",
  "target_audience": "Complete beginners comparing beginner-friendly surf destinations outside Europe",
  "lang": "it",
  "meta_description": "Surf in Senegal per principianti: Ngor Island è la scelta giusta? Onde, sicurezza, coaching e perché un surf camp a Dakar funziona davvero.",
  "content_markdown": "# Surf camp in Senegal per principianti: Ngor Island è una buona scelta?\n\nAlle prime luci del giorno su Ngor Island, l’Atlantico è ancora argento, liscio come vetro, e l’unico traffico è quello di una piroga che scivola oltre gli scogli con un pescatore in piedi a prua. Niente motorini, niente clacson, niente chiringuiti con la musica alta prima di colazione. Solo odore di caffè, salsedine nell’aria e una serie di onde morbide del mattino che si avvolgono dentro la baia. Per chi parte da zero, conta molto più di quanto si pensi. Imparare a surfare è già abbastanza difficile senza aggiungerci acqua fredda, lineup affollate e una scena da spiaggia stressante.\n\nÈ proprio per questo che sempre più surfisti alle prime armi iniziano a guardare oltre l’Europa e verso il Senegal. Dakar riceve swell con buona costanza, l’acqua è calda per gran parte dell’anno e la cultura surf locale ha una storia vera, Ngor Right è entrata nella leggenda grazie a *The Endless Summer* nel 1964. Ma la storia, da sola, non rende una destinazione adatta ai beginner. Quello che conta davvero è altro: puoi imparare in sicurezza, costruire fiducia e goderti il processo? A Ngor Island, spesso la risposta è sì, se scegli il camp giusto e una struttura di coaching fatta bene.\n\n## Perché un surf camp in Senegal per principianti ha senso\n\nSe stai confrontando varie destinazioni per il tuo primo surf trip, il Senegal merita di stare in cima alla lista per un motivo semplice: elimina molte delle barriere che rendono l’apprendimento frustrante. Un buon **senegal surf camp for beginners** offre acqua calda, opzioni di onde gestibili, accesso rapido agli spot e coaching che si adatta al mare giorno per giorno, invece di infilare tutti i beginner nello stesso schema di lezione a prescindere dalle condizioni.\n\nNgor Island è particolarmente interessante perché si trova appena al largo di Dakar ma sembra un altro mondo. La raggiungi in pochi minuti di barca e, all’improvviso, il ritmo cambia. Sull’isola non ci sono auto. Può sembrare un dettaglio, ma per un principiante fa una differenza enorme. Ti svegli, guardi il mare, vai a piedi al punto d’ingresso e l’intera giornata gira intorno a marea, vento e finestre buone per surfare, non a traffico, navette e tempi morti.\n\nIl Senegal è anche uno dei pochi posti dove un surfista alla prima esperienza può trovare, nello stesso viaggio, onde iconiche e una progressione davvero sensata. Molti conoscono Ngor per Ngor Right e Ngor Left, ma il vero vantaggio di soggiornare in un camp serio non è semplicemente “surfare onde famose”. È avere coach locali esperti che sanno decidere quando usare spot più riparati, quando restare nella whitewater e quando un principiante è pronto per la sua prima green wave.\n\nAl **Ngor Surfcamp Teranga**, questo equilibrio tra livello premium e atmosfera accessibile è esattamente il cuore dell’esperienza. Il camp è autorizzato dalla **Federazione Senegalese di Surf**, un dettaglio che conta se per te sono importanti standard seri, legittimità locale e coaching vero, non lezioni improvvisate da vacanza. Per chi inizia, il **video coaching** è un altro grande vantaggio. Molti beginner non hanno la minima idea di cosa stia facendo il loro corpo sulla tavola finché non si vedono in video. Basta una clip per capire perché continui a sbagliare il popup o perché la tua stance sembra instabile.\n\nUn’esperienza da **beginner surf camp Senegal** non dovrebbe ridursi a “sopravvivere” alla prima settimana. Dovrebbe aiutarti a imparare in fretta, sentirti seguito e tornare a casa con la voglia, e la fiducia, di continuare a surfare. Ngor Island offre l’ambiente giusto per questo.\n\n## Le onde sono sicure e adatte a chi è alla prima volta?\n\nQuesta è la domanda più importante, e merita una risposta onesta. Dakar non è un gigantesco parco giochi per principianti dove ogni onda è morbida e indulgente. È una vera surf zone, con reef break, energia di swell e giornate che sono chiaramente migliori per intermediate o advanced. Chi ti dice il contrario ti sta vendendo una fantasia, non un surf trip.\n\nDetto questo, “non facile in assoluto” non significa “non adatto ai beginner”. Significa che la sicurezza dipende dalla lettura delle condizioni, dalla scelta dello spot e dal timing. Ed è proprio qui che un camp ben gestito fa tutta la differenza.\n\nPer un principiante, la sicurezza non dipende solo dalla dimensione dell’onda. Dipende da una combinazione di fattori: quanto è facile entrare e uscire dall’acqua, quanto è ordinata l’onda, quanto è affollata la lineup, quanto è forte la corrente, se il fondo è reef o sabbia, e soprattutto se c’è qualcuno che sa leggere il mare meglio di te. A Ngor, il vantaggio è che i coach locali conoscono davvero il posto. Sanno quali spot funzionano con una certa marea, quali sono troppo esposti con un certo swell e quando è meglio rinunciare a una sessione piuttosto che forzarla.\n\nQuesto approccio è fondamentale per i beginner. Nelle prime fasi, non hai bisogno di onde “epiche”. Hai bisogno di onde leggibili. Hai bisogno di ripetizione. Hai bisogno di un ambiente in cui puoi concentrarti su remata, takeoff, equilibrio e direzione senza sentirti sempre in ritardo o fuori posto. In certe giornate, questo significa lavorare in whitewater. In altre, può voler dire iniziare a prendere piccole green wave in una sezione più morbida e controllata.\n\nIl grande errore che fanno molti alla prima surf trip è pensare che il progresso dipenda dal surfare spot famosi. In realtà, dipende quasi sempre dal surfare condizioni adatte al tuo livello. Un camp serio non costruisce il programma intorno all’ego del cliente o al nome dello spot. Lo costruisce intorno a ciò che ti farà migliorare davvero.\n\nNgor Island può essere una buona scelta per principianti proprio perché offre accesso a diverse opzioni e a coach che sanno filtrare il mare. Ma bisogna essere chiari: non è il posto giusto per chi vuole essere lasciato completamente da solo, noleggiare una tavola e “vedere come va”. Se sei all’inizio, qui rendi al meglio con guida, struttura e supervisione.\n\n## Cosa rende Ngor Island diversa da altre destinazioni per beginner\n\nMolte destinazioni surf per principianti vendono la stessa promessa: sole, acqua calda, lezioni giornaliere e atmosfera rilassata. Ngor Island, però, ha qualcosa di diverso. Non è una località costruita artificialmente intorno al turismo surf. È un luogo con una sua identità, una sua storia e un ritmo quotidiano che esiste a prescindere da chi arriva per fare vacanza.\n\nPer un surfista italiano, questo aspetto pesa. In molte zone d’Europa imparare a surfare significa spesso entrare in acqua con muta spessa, vento onshore, parcheggi pieni e lineup già sature alle nove del mattino. Qui il contesto cambia completamente. L’acqua più calda toglie una grossa barriera fisica e mentale. Il corpo si muove meglio, stai più rilassato, passi più tempo in acqua e sprechi meno energie a combattere il freddo. Per chi è alle prime armi, tutto questo accelera l’apprendimento.\n\nPoi c’è il fattore logistico. Stare su un’isola piccola, senza auto, con vista mare e spot vicini, semplifica la giornata in modo enorme. Meno trasferimenti significa più energie per surfare e recuperare. Significa anche poter osservare il mare più volte durante il giorno, parlare con i coach, capire come cambiano vento e marea e iniziare a sviluppare una cosa che molti beginner sottovalutano: l’occhio.\n\nImparare a surfare non è solo riuscire a stare in piedi. È iniziare a leggere il mare. Vedere se una sezione chiude, capire dove si forma il picco, intuire quando una corrente ti sposta. In un posto come Ngor, dove il surf è parte della vita quotidiana e non solo un’attività da resort, questo apprendimento succede in modo più naturale.\n\nE poi c’è la componente culturale. Il Senegal ha un’ospitalità che si sente davvero, e la parola “teranga” non è uno slogan messo lì per marketing: è un modo di accogliere. Per molti viaggiatori italiani, soprattutto quelli che cercano qualcosa di più di una semplice vacanza standardizzata, questo fa la differenza. Ti senti ospite, non solo cliente.\n\n## Il ruolo del coaching: perché per i beginner conta più dello spot\n\nQuando si parla di prime surf trip, c’è una tendenza a concentrarsi quasi solo sulla destinazione. Ma per un principiante, il fattore decisivo raramente è lo spot in sé. È il coaching.\n\nUn buon coach non si limita a dirti “pagaia più forte” o “alzati prima”. Ti aiuta a capire *quando* remare, *dove* posizionarti, *quale* onda prendere e *perché* stai sbagliando un gesto. Questa differenza è enorme, soprattutto nei primi giorni, quando ogni movimento sembra arrivare troppo in fretta.\n\nAl Ngor Surfcamp Teranga, il valore aggiunto sta proprio in questa impostazione. Il coaching non è una formalità appiccicata al soggiorno: è parte centrale dell’esperienza. Per un beginner, questo significa progressione reale. Significa non perdere tre sessioni a ripetere lo stesso errore senza accorgertene. Significa ricevere feedback chiari, pratici e immediati.\n\nIl **video coaching** è particolarmente utile perché rende visibile ciò che in acqua senti solo in modo confuso. Magari sei convinto di fare un popup rapido, poi ti rivedi e capisci che stai appoggiando il ginocchio, guardando in basso o aprendo troppo le spalle. Oppure pensi di essere centrato sulla tavola e scopri che stai partendo sempre troppo indietro. Vedere questi dettagli accelera tantissimo.\n\nPer i beginner, inoltre, il coaching serve anche a gestire la parte mentale. All’inizio è normalissimo avere paura di sbagliare, di prendere una schiuma in faccia, di intralciare gli altri o di non capire il timing. Un buon istruttore sa abbassare il livello di stress, spezzare l’apprendimento in passaggi semplici e costruire fiducia sessione dopo sessione.\n\nQuesta è una delle ragioni per cui un camp autorizzato e strutturato conta più di quanto sembri. Non stai solo pagando un letto e due lezioni. Stai investendo in un contesto dove il tuo apprendimento viene preso sul serio.\n\n## Vita al camp: comfort premium, ritmo semplice\n\nUna delle cose più sottovalutate nelle surf trip per principianti è il recupero. Se dormi male, mangi male o passi metà giornata in spostamenti, impari peggio. Semplice. Per questo la qualità del camp ha un impatto diretto sul tuo surf, non solo sul comfort.\n\nAl Ngor Surfcamp Teranga, il lato premium non significa atmosfera fredda o impostata. Significa avere ciò che serve per stare bene e mantenere energie alte durante la settimana: camere curate, **vista mare**, una **pool** per rilassarsi o sciogliere il corpo dopo le sessioni, e un ambiente tranquillo dove il surf resta al centro della giornata.\n\nIl fatto che sull’isola non ci siano auto contribuisce tantissimo a questa sensazione. Il rumore di fondo sparisce. Le giornate diventano più semplici. Colazione, check del mare, sessione, pausa, review video, tramonto. Per un beginner è quasi il contesto ideale, perché riduce stimoli inutili e ti permette di concentrarti su poche cose fatte bene.\n\nAnche dal punto di vista pratico, questo ritmo aiuta. Quando stai imparando, sei spesso stanco in modi nuovi: spalle affaticate, gambe tese, testa piena di informazioni. Tornare in un posto calmo, bello e funzionale non è un lusso secondario. È parte dell’esperienza.\n\n## A chi consigliamo davvero Ngor Island per imparare a surfare\n\nNgor Island è una buona scelta soprattutto per tre tipi di viaggiatori.\n\nIl primo è il principiante assoluto che vuole iniziare nel modo giusto, con supporto vero e senza il caos di molte destinazioni europee. Se vuoi acqua più calda, un contesto rilassato e coaching strutturato, qui hai ottime possibilità di partire bene.\n\nIl secondo è il beginner che ha già fatto qualche lezione in Italia, Portogallo o Francia ma non è ancora autonomo. Magari hai preso qualche onda in whitewater, forse qualcuna green, ma senti di non avere ancora continuità. In questo caso, una settimana ben organizzata a Ngor può essere il passaggio che ti manca per consolidare le basi.\n\nIl terzo è il viaggiatore che cerca una surf trip con più carattere. Non solo surf school, aperitivo e dormitorio, ma un luogo con identità, storia e un rapporto più diretto con il territorio.\n\nChi invece potrebbe non trovarsi al meglio? Chi vuole una destinazione super facile e totalmente “soft” in ogni condizione, oppure chi non ha interesse per il coaching e preferisce arrangiarsi da solo. Ngor dà il meglio di sé quando la vivi con umiltà e con la voglia di imparare davvero.\n\n## Quindi: Ngor Island è una buona scelta per beginner?\n\nSì, per molti principianti Ngor Island è una scelta molto valida, ma con una condizione importante: va affrontata nel modo giusto.\n\nNon è una destinazione da cartolina dove tutto è automaticamente facile. È un luogo surf autentico, con onde serie, storia vera e condizioni che cambiano. Proprio per questo, se ti affidi a un camp competente, può offrirti molto più di una classica settimana introduttiva. Può darti basi solide, fiducia e una comprensione più reale del surf.\n\nÈ qui che il **Ngor Surfcamp Teranga** si distingue. L’unione tra posizione sull’isola, comfort premium, licenza della **Federazione Senegalese di Surf**, **video coaching** e conoscenza locale crea un contesto particolarmente forte per chi inizia. Non si tratta solo di fare lezioni. Si tratta di imparare bene, in un posto che ti mette nelle condizioni giuste per farlo.\n\nSe stai cercando un **senegal surf camp for beginners** che unisca onde di livello mondiale, atmosfera rilassata, acqua calda e coaching serio, Ngor Island merita assolutamente attenzione.\n\nPer informazioni e prenotazioni: **+221 78 925 70 25**  \nSito: **surfcampsenegal.com**",
  "word_count_estimate": 2234,
  "original_en_slug": "senegal-surf-camp-for-beginners"
}